replicantx/__init__.py
replicantx/cli.py
replicantx/models.py
replicantx/auth/__init__.py
replicantx/auth/base.py
replicantx/auth/jwt.py
replicantx/auth/noop.py
replicantx/auth/supabase.py
replicantx/reporters/__init__.py
replicantx/reporters/json.py
replicantx/reporters/markdown.py
replicantx/scenarios/__init__.py
replicantx/scenarios/agent.py
replicantx/scenarios/basic.py
replicantx/scenarios/replicant.py
replicantx/tools/__init__.py
replicantx/tools/http_client.py
replicantx/tools/payload_formatter.py
replicantx/tools/session_manager.py
replicantx-0.1.10.dist-info/licenses/LICENSE
replicantx-0.1.10.dist-info/METADATA
replicantx-0.1.10.dist-info/WHEEL
replicantx-0.1.10.dist-info/entry_points.txt
replicantx-0.1.10.dist-info/top_level.txt
replicantx-0.1.10.dist-info/RECORD
