Metadata-Version: 2.4
Name: replicantx
Version: 0.1.10
Summary: End-to-end testing harness for AI agents via web service API
Author-email: Helix Technologies Limited <team@replicantx.org>
License-Expression: Apache-2.0
Project-URL: Homepage, https://github.com/helixtechnologies/replicantx
Project-URL: Documentation, https://replicantx.org
Project-URL: Repository, https://github.com/helixtechnologies/replicantx
Project-URL: Issues, https://github.com/helixtechnologies/replicantx/issues
Keywords: ai,agent,testing,e2e,api
Classifier: Development Status :: 4 - Beta
Classifier: Intended Audience :: Developers
Classifier: Programming Language :: Python :: 3
Classifier: Programming Language :: Python :: 3.11
Classifier: Topic :: Software Development :: Testing
Classifier: Topic :: Internet :: WWW/HTTP :: HTTP Servers
Requires-Python: >=3.11
License-File: LICENSE
Requires-Dist: pydantic>=2.11.7
Requires-Dist: typer>=0.16.0
Requires-Dist: httpx>=0.28.1
Requires-Dist: PyYAML>=6.0.2
Requires-Dist: supabase>=2.18.0
Requires-Dist: jinja2>=3.1.6
Requires-Dist: rich>=14.1.0
Requires-Dist: pydantic-ai>=0.6.2
Requires-Dist: python-dotenv>=1.1.1
Requires-Dist: typing-extensions>=4.14.1
Provides-Extra: cli
Requires-Dist: typer[all]>=0.16.0; extra == "cli"
Provides-Extra: dev
Requires-Dist: pytest>=8.0.0; extra == "dev"
Requires-Dist: pytest-asyncio>=0.23.0; extra == "dev"
Requires-Dist: black>=24.0.0; extra == "dev"
Requires-Dist: isort>=5.12.0; extra == "dev"
Requires-Dist: mypy>=1.8.0; extra == "dev"
Provides-Extra: openai
Requires-Dist: openai>=1.99.3; extra == "openai"
Provides-Extra: anthropic
Requires-Dist: anthropic>=0.61.0; extra == "anthropic"
Provides-Extra: all
Requires-Dist: typer[all]>=0.16.0; extra == "all"
Requires-Dist: openai>=1.99.3; extra == "all"
Requires-Dist: anthropic>=0.61.0; extra == "all"
Dynamic: license-file
